{
  "opencollection": "1.0.0",
  "info": {
    "name": "Microsoft Azure Azure Resource Manager API",
    "version": "2024-03-01"
  },
  "request": {
    "auth": {
      "type": "oauth2",
      "flow": "implicit",
      "authorizationUrl": "https://login.microsoftonline.com/common/oauth2/authorize",
      "credentials": {
        "clientId": "{{clientId}}"
      }
    }
  },
  "items": [
    {
      "info": {
        "name": "Subscriptions",
        "type": "folder"
      },
      "items": [
        {
          "info": {
            "name": "Microsoft Azure List All Subscriptions",
            "type": "http"
          },
          "http": {
            "method": "GET",
            "url": "https://management.azure.com/subscriptions",
            "params": [
              {
                "name": "api-version",
                "value": "",
                "type": "query",
                "description": "The API version to use for this operation."
              }
            ]
          },
          "docs": "Gets all subscriptions for the authenticated tenant."
        },
        {
          "info": {
            "name": "Microsoft Azure Get a Subscription",
            "type": "http"
          },
          "http": {
            "method": "GET",
            "url": "https://management.azure.com/subscriptions/:subscriptionId",
            "params": [
              {
                "name": "subscriptionId",
                "value": "",
                "type": "path",
                "description": "The ID of the target subscription."
              },
              {
                "name": "api-version",
                "value": "",
                "type": "query",
                "description": "The API version to use for this operation."
              }
            ]
          },
          "docs": "Gets details about the specified subscription."
        }
      ]
    },
    {
      "info": {
        "name": "Resource Groups",
        "type": "folder"
      },
      "items": [
        {
          "info": {
            "name": "Microsoft Azure List Resource Groups",
            "type": "http"
          },
          "http": {
            "method": "GET",
            "url": "https://management.azure.com/subscriptions/:subscriptionId/resourcegroups",
            "params": [
              {
                "name": "subscriptionId",
                "value": "",
                "type": "path",
                "description": "The ID of the target subscription."
              },
              {
                "name": "api-version",
                "value": "",
                "type": "query",
                "description": "The API version to use for this operation."
              },
              {
                "name": "$filter",
                "value": "example_value",
                "type": "query",
                "description": "The filter to apply on the operation using OData syntax."
              },
              {
                "name": "$top",
                "value": "10",
                "type": "query",
                "description": "The number of results to return."
              }
            ]
          },
          "docs": "Gets all the resource groups for a subscription."
        },
        {
          "info": {
            "name": "Microsoft Azure Get a Resource Group",
            "type": "http"
          },
          "http": {
            "method": "GET",
            "url": "https://management.azure.com/subscriptions/:subscriptionId/resourcegroups/:resourceGroupName",
            "params": [
              {
                "name": "subscriptionId",
                "value": "",
                "type": "path",
                "description": "The ID of the target subscription."
              },
              {
                "name": "resourceGroupName",
                "value": "",
                "type": "path",
                "description": "The name of the resource group. The name is case insensitive."
              },
              {
                "name": "api-version",
                "value": "",
                "type": "query",
                "description": "The API version to use for this operation."
              }
            ]
          },
          "docs": "Gets a resource group by name."
        },
        {
          "info": {
            "name": "Microsoft Azure Create or Update a Resource Group",
            "type": "http"
          },
          "http": {
            "method": "PUT",
            "url": "https://management.azure.com/subscriptions/:subscriptionId/resourcegroups/:resourceGroupName",
            "params": [
              {
                "name": "subscriptionId",
                "value": "",
                "type": "path",
                "description": "The ID of the target subscription."
              },
              {
                "name": "resourceGroupName",
                "value": "",
                "type": "path",
                "description": "The name of the resource group. The name is case insensitive."
              },
              {
                "name": "api-version",
                "value": "",
                "type": "query",
                "description": "The API version to use for this operation."
              }
            ],
            "body": {
              "type": "json",
              "data": "{}"
            }
          },
          "docs": "Creates or updates a resource group."
        },
        {
          "info": {
            "name": "Microsoft Azure Update a Resource Group",
            "type": "http"
          },
          "http": {
            "method": "PATCH",
            "url": "https://management.azure.com/subscriptions/:subscriptionId/resourcegroups/:resourceGroupName",
            "params": [
              {
                "name": "subscriptionId",
                "value": "",
                "type": "path",
                "description": "The ID of the target subscription."
              },
              {
                "name": "resourceGroupName",
                "value": "",
                "type": "path",
                "description": "The name of the resource group. The name is case insensitive."
              },
              {
                "name": "api-version",
                "value": "",
                "type": "query",
                "description": "The API version to use for this operation."
              }
            ],
            "body": {
              "type": "json",
              "data": "{}"
            }
          },
          "docs": "Updates a resource group. Resource groups can be updated by patching the resource group properties, such as tags."
        },
        {
          "info": {
            "name": "Microsoft Azure Delete a Resource Group",
            "type": "http"
          },
          "http": {
            "method": "DELETE",
            "url": "https://management.azure.com/subscriptions/:subscriptionId/resourcegroups/:resourceGroupName",
            "params": [
              {
                "name": "subscriptionId",
                "value": "",
                "type": "path",
                "description": "The ID of the target subscription."
              },
              {
                "name": "resourceGroupName",
                "value": "",
                "type": "path",
                "description": "The name of the resource group. The name is case insensitive."
              },
              {
                "name": "api-version",
                "value": "",
                "type": "query",
                "description": "The API version to use for this operation."
              },
              {
                "name": "forceDeletionTypes",
                "value": "example_value",
                "type": "query",
                "description": "The resource types that should be force deleted. Comma-separated list of resource type names."
              }
            ]
          },
          "docs": "Deletes a resource group. When you delete a resource group, all of its resources are also deleted."
        }
      ]
    },
    {
      "info": {
        "name": "Resources",
        "type": "folder"
      },
      "items": [
        {
          "info": {
            "name": "Microsoft Azure List All Resources in a Subscription",
            "type": "http"
          },
          "http": {
            "method": "GET",
            "url": "https://management.azure.com/subscriptions/:subscriptionId/resources",
            "params": [
              {
                "name": "subscriptionId",
                "value": "",
                "type": "path",
                "description": "The ID of the target subscription."
              },
              {
                "name": "api-version",
                "value": "",
                "type": "query",
                "description": "The API version to use for this operation."
              },
              {
                "name": "$filter",
                "value": "example_value",
                "type": "query",
                "description": "The filter to apply on the operation using OData syntax."
              },
              {
                "name": "$expand",
                "value": "example_value",
                "type": "query",
                "description": "Comma-separated list of additional properties to be included in the response. Valid values include createdTime, changedTime, and provisioningState."
              },
              {
                "name": "$top",
                "value": "10",
                "type": "query",
                "description": "The number of results to return."
              }
            ]
          },
          "docs": "Get all the resources in a subscription."
        },
        {
          "info": {
            "name": "Microsoft Azure List Resources in a Resource Group",
            "type": "http"
          },
          "http": {
            "method": "GET",
            "url": "https://management.azure.com/subscriptions/:subscriptionId/resourcegroups/:resourceGroupName/resources",
            "params": [
              {
                "name": "subscriptionId",
                "value": "",
                "type": "path",
                "description": "The ID of the target subscription."
              },
              {
                "name": "resourceGroupName",
                "value": "",
                "type": "path",
                "description": "The name of the resource group. The name is case insensitive."
              },
              {
                "name": "api-version",
                "value": "",
                "type": "query",
                "description": "The API version to use for this operation."
              },
              {
                "name": "$filter",
                "value": "example_value",
                "type": "query",
                "description": "The filter to apply on the operation using OData syntax."
              },
              {
                "name": "$top",
                "value": "10",
                "type": "query",
                "description": "The number of results to return."
              }
            ]
          },
          "docs": "Get all the resources for a resource group."
        }
      ]
    },
    {
      "info": {
        "name": "Deployments",
        "type": "folder"
      },
      "items": [
        {
          "info": {
            "name": "Microsoft Azure Get a Deployment",
            "type": "http"
          },
          "http": {
            "method": "GET",
            "url": "https://management.azure.com/subscriptions/:subscriptionId/resourcegroups/:resourceGroupName/deployments/:deploymentName",
            "params": [
              {
                "name": "subscriptionId",
                "value": "",
                "type": "path",
                "description": "The ID of the target subscription."
              },
              {
                "name": "resourceGroupName",
                "value": "",
                "type": "path",
                "description": "The name of the resource group. The name is case insensitive."
              },
              {
                "name": "deploymentName",
                "value": "example_value",
                "type": "path",
                "description": "The name of the deployment."
              },
              {
                "name": "api-version",
                "value": "",
                "type": "query",
                "description": "The API version to use for this operation."
              }
            ]
          },
          "docs": "Gets a deployment by name."
        },
        {
          "info": {
            "name": "Microsoft Azure Create or Update a Deployment",
            "type": "http"
          },
          "http": {
            "method": "PUT",
            "url": "https://management.azure.com/subscriptions/:subscriptionId/resourcegroups/:resourceGroupName/deployments/:deploymentName",
            "params": [
              {
                "name": "subscriptionId",
                "value": "",
                "type": "path",
                "description": "The ID of the target subscription."
              },
              {
                "name": "resourceGroupName",
                "value": "",
                "type": "path",
                "description": "The name of the resource group. The name is case insensitive."
              },
              {
                "name": "deploymentName",
                "value": "example_value",
                "type": "path",
                "description": "The name of the deployment."
              },
              {
                "name": "api-version",
                "value": "",
                "type": "query",
                "description": "The API version to use for this operation."
              }
            ],
            "body": {
              "type": "json",
              "data": "{}"
            }
          },
          "docs": "Deploys resources at resource group scope. You can provide the template and parameters directly in the request or link to JSON files."
        }
      ]
    },
    {
      "info": {
        "name": "Providers",
        "type": "folder"
      },
      "items": [
        {
          "info": {
            "name": "Microsoft Azure List Resource Providers",
            "type": "http"
          },
          "http": {
            "method": "GET",
            "url": "https://management.azure.com/subscriptions/:subscriptionId/providers",
            "params": [
              {
                "name": "subscriptionId",
                "value": "",
                "type": "path",
                "description": "The ID of the target subscription."
              },
              {
                "name": "api-version",
                "value": "",
                "type": "query",
                "description": "The API version to use for this operation."
              },
              {
                "name": "$expand",
                "value": "example_value",
                "type": "query",
                "description": "The properties to include in the results. For example, use resourceTypes/aliases to get the aliases for resource types."
              }
            ]
          },
          "docs": "Gets all resource providers for a subscription."
        }
      ]
    },
    {
      "info": {
        "name": "Default",
        "type": "folder"
      },
      "items": [
        {
          "info": {
            "name": "Microsoft Azure List Predefined Tag Names",
            "type": "http"
          },
          "http": {
            "method": "GET",
            "url": "https://management.azure.com/subscriptions/:subscriptionId/tagNames",
            "params": [
              {
                "name": "subscriptionId",
                "value": "",
                "type": "path",
                "description": "The ID of the target subscription."
              },
              {
                "name": "api-version",
                "value": "",
                "type": "query",
                "description": "The API version to use for this operation."
              }
            ]
          },
          "docs": "Gets a summary of tag usage under the subscription. This operation performs a union of predefined tags, resource tags, resource group tags and subscription tags."
        }
      ]
    }
  ],
  "bundled": true
}