{
  "info": {
    "_postman_id": "72fa4847-8a6f-4219-904d-5a6dc13f08b4",
    "name": "Microsoft Azure Azure SQL Database Import/Export spec",
    "description": "Provides create and read functionality for Import/Export operations on Azure SQL databases.",
    "schema": "https://schema.getpostman.com/json/collection/v2.1.0/collection.json",
    "createdAt": "2026-06-05T15:26:40.000Z",
    "updatedAt": "2026-06-05T15:26:41.000Z",
    "lastUpdatedBy": "35240",
    "uid": "35240-72fa4847-8a6f-4219-904d-5a6dc13f08b4"
  },
  "item": [
    {
      "name": "subscriptions",
      "item": [
        {
          "name": "{subscriptionId}",
          "item": [
            {
              "name": "resourceGroups",
              "item": [
                {
                  "name": "{resourceGroupName}",
                  "item": [
                    {
                      "name": "providers",
                      "item": [
                        {
                          "name": "Microsoft.Sql",
                          "item": [
                            {
                              "name": "servers",
                              "item": [
                                {
                                  "name": "{serverName}",
                                  "item": [
                                    {
                                      "name": "import",
                                      "item": [
                                        {
                                          "name": "Microsoft Azure Post Subscriptions Subscriptionid Resourcegroups Resourcegroupname Providers Microsoft Sql Servers Servername Import",
                                          "id": "774d5aed-22e0-4739-a4a1-29e57f251186",
                                          "protocolProfileBehavior": {
                                            "disableBodyPruning": true
                                          },
                                          "request": {
                                            "method": "POST",
                                            "header": [
                                              {
                                                "key": "Content-Type",
                                                "value": "application/json"
                                              },
                                              {
                                                "key": "Accept",
                                                "value": "application/json"
                                              }
                                            ],
                                            "body": {
                                              "mode": "raw",
                                              "raw": "{\n  \"administratorLogin\": \"<string>\",\n  \"administratorLoginPassword\": \"<string>\",\n  \"databaseName\": \"amet commodo\",\n  \"edition\": \"PremiumRS\",\n  \"maxSizeBytes\": \"proident dolor\",\n  \"serviceObjectiveName\": \"DS2000\",\n  \"storageKey\": \"<string>\",\n  \"storageKeyType\": \"SharedAccessKey\",\n  \"storageUri\": \"<string>\",\n  \"authenticationType\": \"SQL\"\n}",
                                              "options": {
                                                "raw": {
                                                  "headerFamily": "json",
                                                  "language": "json"
                                                }
                                              }
                                            },
                                            "url": {
                                              "raw": "{{baseUrl}}/subscriptions/:subscriptionId/resourceGroups/:resourceGroupName/providers/Microsoft.Sql/servers/:serverName/import",
                                              "host": [
                                                "{{baseUrl}}"
                                              ],
                                              "path": [
                                                "subscriptions",
                                                ":subscriptionId",
                                                "resourceGroups",
                                                ":resourceGroupName",
                                                "providers",
                                                "Microsoft.Sql",
                                                "servers",
                                                ":serverName",
                                                "import"
                                              ],
                                              "variable": [
                                                {
                                                  "id": "79d2bd3f-2cd3-4d28-9fb3-6f78eff7e5a4",
                                                  "key": "subscriptionId"
                                                },
                                                {
                                                  "id": "bac25c43-4e6a-4b60-a787-1ae0170350cf",
                                                  "key": "resourceGroupName"
                                                },
                                                {
                                                  "id": "1fafcc76-78f8-4f9f-8ac9-3e3bc7e85477",
                                                  "key": "serverName",
                                                  "value": "<string>",
                                                  "description": "(Required) The name of the server."
                                                }
                                              ]
                                            },
                                            "description": "Imports a bacpac into a new database. "
                                          },
                                          "response": [
                                            {
                                              "id": "adf49986-de78-43aa-9b3e-d1bd54ec17f3",
                                              "name": "OK",
                                              "originalRequest": {
                                                "method": "POST",
                                                "header": [
                                                  {
                                                    "key": "Content-Type",
                                                    "value": "application/json"
                                                  },
                                                  {
                                                    "key": "Accept",
                                                    "value": "application/json"
                                                  }
                                                ],
                                                "body": {
                                                  "mode": "raw",
                                                  "raw": "{\n  \"administratorLogin\": \"<string>\",\n  \"administratorLoginPassword\": \"<string>\",\n  \"databaseName\": \"amet commodo\",\n  \"edition\": \"PremiumRS\",\n  \"maxSizeBytes\": \"proident dolor\",\n  \"serviceObjectiveName\": \"DS2000\",\n  \"storageKey\": \"<string>\",\n  \"storageKeyType\": \"SharedAccessKey\",\n  \"storageUri\": \"<string>\",\n  \"authenticationType\": \"SQL\"\n}",
                                                  "options": {
                                                    "raw": {
                                                      "headerFamily": "json",
                                                      "language": "json"
                                                    }
                                                  }
                                                },
                                                "url": {
                                                  "raw": "{{baseUrl}}/subscriptions/:subscriptionId/resourceGroups/:resourceGroupName/providers/Microsoft.Sql/servers/:serverName/import",
                                                  "host": [
                                                    "{{baseUrl}}"
                                                  ],
                                                  "path": [
                                                    "subscriptions",
                                                    ":subscriptionId",
                                                    "resourceGroups",
                                                    ":resourceGroupName",
                                                    "providers",
                                                    "Microsoft.Sql",
                                                    "servers",
                                                    ":serverName",
                                                    "import"
                                                  ],
                                                  "variable": [
                                                    {
                                                      "key": "subscriptionId"
                                                    },
                                                    {
                                                      "key": "resourceGroupName"
                                                    },
                                                    {
                                                      "key": "serverName"
                                                    }
                                                  ]
                                                }
                                              },
                                              "status": "OK",
                                              "code": 200,
                                              "_postman_previewlanguage": "json",
                                              "header": [
                                                {
                                                  "key": "Content-Type",
                                                  "value": "application/json"
                                                }
                                              ],
                                              "cookie": [],
                                              "responseTime": null,
                                              "body": "{\n  \"properties\": {}\n}",
                                              "createdAt": "2026-06-05T15:26:41.000Z",
                                              "updatedAt": "2026-06-05T15:26:41.000Z",
                                              "uid": "35240-adf49986-de78-43aa-9b3e-d1bd54ec17f3"
                                            },
                                            {
                                              "id": "4dc2bd13-4089-43f8-8603-40744a6c05fd",
                                              "name": "Accepted",
                                              "originalRequest": {
                                                "method": "POST",
                                                "header": [
                                                  {
                                                    "key": "Content-Type",
                                                    "value": "application/json"
                                                  }
                                                ],
                                                "body": {
                                                  "mode": "raw",
                                                  "raw": "{\n  \"administratorLogin\": \"<string>\",\n  \"administratorLoginPassword\": \"<string>\",\n  \"databaseName\": \"amet commodo\",\n  \"edition\": \"PremiumRS\",\n  \"maxSizeBytes\": \"proident dolor\",\n  \"serviceObjectiveName\": \"DS2000\",\n  \"storageKey\": \"<string>\",\n  \"storageKeyType\": \"SharedAccessKey\",\n  \"storageUri\": \"<string>\",\n  \"authenticationType\": \"SQL\"\n}",
                                                  "options": {
                                                    "raw": {
                                                      "headerFamily": "json",
                                                      "language": "json"
                                                    }
                                                  }
                                                },
                                                "url": {
                                                  "raw": "{{baseUrl}}/subscriptions/:subscriptionId/resourceGroups/:resourceGroupName/providers/Microsoft.Sql/servers/:serverName/import",
                                                  "host": [
                                                    "{{baseUrl}}"
                                                  ],
                                                  "path": [
                                                    "subscriptions",
                                                    ":subscriptionId",
                                                    "resourceGroups",
                                                    ":resourceGroupName",
                                                    "providers",
                                                    "Microsoft.Sql",
                                                    "servers",
                                                    ":serverName",
                                                    "import"
                                                  ],
                                                  "variable": [
                                                    {
                                                      "key": "subscriptionId"
                                                    },
                                                    {
                                                      "key": "resourceGroupName"
                                                    },
                                                    {
                                                      "key": "serverName"
                                                    }
                                                  ]
                                                }
                                              },
                                              "status": "Accepted",
                                              "code": 202,
                                              "_postman_previewlanguage": "text",
                                              "header": [],
                                              "cookie": [],
                                              "responseTime": null,
                                              "body": null,
                                              "createdAt": "2026-06-05T15:26:41.000Z",
                                              "updatedAt": "2026-06-05T15:26:41.000Z",
                                              "uid": "35240-4dc2bd13-4089-43f8-8603-40744a6c05fd"
                                            }
                                          ],
                                          "createdAt": "2026-06-05T15:26:41.000Z",
                                          "updatedAt": "2026-06-05T15:26:41.000Z",
                                          "uid": "35240-774d5aed-22e0-4739-a4a1-29e57f251186"
                                        }
                                      ],
                                      "id": "9beca18b-5d59-468c-8d8d-e45e9782b98b",
                                      "createdAt": "2026-06-05T15:26:41.000Z",
                                      "updatedAt": "2026-06-05T15:26:41.000Z",
                                      "uid": "35240-9beca18b-5d59-468c-8d8d-e45e9782b98b"
                                    },
                                    {
                                      "name": "databases",
                                      "item": [
                                        {
                                          "name": "{databaseName}",
                                          "item": [
                                            {
                                              "name": "extensions",
                                              "item": [
                                                {
                                                  "name": "{extensionName}",
                                                  "item": [
                                                    {
                                                      "name": "Microsoft Azure Put Subscriptions Subscriptionid Resourcegroups Resourcegroupname Providers Microsoft Sql Servers Servername Databases Databasename Extensions Extensionname",
                                                      "id": "974f93d5-6efd-4bcb-bc6c-380d12e40aa4",
                                                      "protocolProfileBehavior": {
                                                        "disableBodyPruning": true
                                                      },
                                                      "request": {
                                                        "method": "PUT",
                                                        "header": [
                                                          {
                                                            "key": "Content-Type",
                                                            "value": "application/json"
                                                          },
                                                          {
                                                            "key": "Accept",
                                                            "value": "application/json"
                                                          }
                                                        ],
                                                        "body": {
                                                          "mode": "raw",
                                                          "raw": "{\n  \"name\": \"<string>\",\n  \"type\": \"<string>\",\n  \"properties\": {\n    \"administratorLogin\": \"<string>\",\n    \"administratorLoginPassword\": \"<string>\",\n    \"operationMode\": \"Import\",\n    \"storageKey\": \"<string>\",\n    \"storageKeyType\": \"SharedAccessKey\",\n    \"storageUri\": \"<string>\",\n    \"authenticationType\": \"SQL\"\n  }\n}",
                                                          "options": {
                                                            "raw": {
                                                              "headerFamily": "json",
                                                              "language": "json"
                                                            }
                                                          }
                                                        },
                                                        "url": {
                                                          "raw": "{{baseUrl}}/subscriptions/:subscriptionId/resourceGroups/:resourceGroupName/providers/Microsoft.Sql/servers/:serverName/databases/:databaseName/extensions/:extensionName",
                                                          "host": [
                                                            "{{baseUrl}}"
                                                          ],
                                                          "path": [
                                                            "subscriptions",
                                                            ":subscriptionId",
                                                            "resourceGroups",
                                                            ":resourceGroupName",
                                                            "providers",
                                                            "Microsoft.Sql",
                                                            "servers",
                                                            ":serverName",
                                                            "databases",
                                                            ":databaseName",
                                                            "extensions",
                                                            ":extensionName"
                                                          ],
                                                          "variable": [
                                                            {
                                                              "id": "adee0869-62f5-4510-a64b-10bf3b7d6ecd",
                                                              "key": "subscriptionId"
                                                            },
                                                            {
                                                              "id": "de930f63-085e-406e-b433-79166260d336",
                                                              "key": "resourceGroupName"
                                                            },
                                                            {
                                                              "id": "186c4f4e-e7aa-4597-8319-11459c727800",
                                                              "key": "serverName",
                                                              "value": "<string>",
                                                              "description": "(Required) The name of the server."
                                                            },
                                                            {
                                                              "id": "64c4fffb-bd38-4e4d-8538-c192c02d222f",
                                                              "key": "databaseName",
                                                              "value": "<string>",
                                                              "description": "(Required) The name of the database to import into"
                                                            },
                                                            {
                                                              "id": "fd8bde45-170a-4a39-b89b-4381cfaccec7",
                                                              "key": "extensionName",
                                                              "value": "import",
                                                              "description": "(Required) The name of the operation to perform"
                                                            }
                                                          ]
                                                        },
                                                        "description": "Creates an import operation that imports a bacpac into an existing database. The existing database must be empty."
                                                      },
                                                      "response": [
                                                        {
                                                          "id": "7d6afdab-a9c9-4b06-aa36-7618ae81fc2e",
                                                          "name": "OK",
                                                          "originalRequest": {
                                                            "method": "PUT",
                                                            "header": [
                                                              {
                                                                "key": "Content-Type",
                                                                "value": "application/json"
                                                              },
                                                              {
                                                                "key": "Accept",
                                                                "value": "application/json"
                                                              }
                                                            ],
                                                            "body": {
                                                              "mode": "raw",
                                                              "raw": "{\n  \"name\": \"<string>\",\n  \"type\": \"<string>\",\n  \"properties\": {\n    \"administratorLogin\": \"<string>\",\n    \"administratorLoginPassword\": \"<string>\",\n    \"operationMode\": \"Import\",\n    \"storageKey\": \"<string>\",\n    \"storageKeyType\": \"SharedAccessKey\",\n    \"storageUri\": \"<string>\",\n    \"authenticationType\": \"SQL\"\n  }\n}",
                                                              "options": {
                                                                "raw": {
                                                                  "headerFamily": "json",
                                                                  "language": "json"
                                                                }
                                                              }
                                                            },
                                                            "url": {
                                                              "raw": "{{baseUrl}}/subscriptions/:subscriptionId/resourceGroups/:resourceGroupName/providers/Microsoft.Sql/servers/:serverName/databases/:databaseName/extensions/:extensionName",
                                                              "host": [
                                                                "{{baseUrl}}"
                                                              ],
                                                              "path": [
                                                                "subscriptions",
                                                                ":subscriptionId",
                                                                "resourceGroups",
                                                                ":resourceGroupName",
                                                                "providers",
                                                                "Microsoft.Sql",
                                                                "servers",
                                                                ":serverName",
                                                                "databases",
                                                                ":databaseName",
                                                                "extensions",
                                                                ":extensionName"
                                                              ],
                                                              "variable": [
                                                                {
                                                                  "key": "subscriptionId"
                                                                },
                                                                {
                                                                  "key": "resourceGroupName"
                                                                },
                                                                {
                                                                  "key": "serverName"
                                                                },
                                                                {
                                                                  "key": "databaseName"
                                                                },
                                                                {
                                                                  "key": "extensionName"
                                                                }
                                                              ]
                                                            }
                                                          },
                                                          "status": "Created",
                                                          "code": 201,
                                                          "_postman_previewlanguage": "json",
                                                          "header": [
                                                            {
                                                              "key": "Content-Type",
                                                              "value": "application/json"
                                                            }
                                                          ],
                                                          "cookie": [],
                                                          "responseTime": null,
                                                          "body": "{\n  \"properties\": {}\n}",
                                                          "createdAt": "2026-06-05T15:26:41.000Z",
                                                          "updatedAt": "2026-06-05T15:26:41.000Z",
                                                          "uid": "35240-7d6afdab-a9c9-4b06-aa36-7618ae81fc2e"
                                                        },
                                                        {
                                                          "id": "271b3641-616e-45ed-9f8d-cd7851b2d46c",
                                                          "name": "Accepted",
                                                          "originalRequest": {
                                                            "method": "PUT",
                                                            "header": [
                                                              {
                                                                "key": "Content-Type",
                                                                "value": "application/json"
                                                              }
                                                            ],
                                                            "body": {
                                                              "mode": "raw",
                                                              "raw": "{\n  \"name\": \"<string>\",\n  \"type\": \"<string>\",\n  \"properties\": {\n    \"administratorLogin\": \"<string>\",\n    \"administratorLoginPassword\": \"<string>\",\n    \"operationMode\": \"Import\",\n    \"storageKey\": \"<string>\",\n    \"storageKeyType\": \"SharedAccessKey\",\n    \"storageUri\": \"<string>\",\n    \"authenticationType\": \"SQL\"\n  }\n}",
                                                              "options": {
                                                                "raw": {
                                                                  "headerFamily": "json",
                                                                  "language": "json"
                                                                }
                                                              }
                                                            },
                                                            "url": {
                                                              "raw": "{{baseUrl}}/subscriptions/:subscriptionId/resourceGroups/:resourceGroupName/providers/Microsoft.Sql/servers/:serverName/databases/:databaseName/extensions/:extensionName",
                                                              "host": [
                                                                "{{baseUrl}}"
                                                              ],
                                                              "path": [
                                                                "subscriptions",
                                                                ":subscriptionId",
                                                                "resourceGroups",
                                                                ":resourceGroupName",
                                                                "providers",
                                                                "Microsoft.Sql",
                                                                "servers",
                                                                ":serverName",
                                                                "databases",
                                                                ":databaseName",
                                                                "extensions",
                                                                ":extensionName"
                                                              ],
                                                              "variable": [
                                                                {
                                                                  "key": "subscriptionId"
                                                                },
                                                                {
                                                                  "key": "resourceGroupName"
                                                                },
                                                                {
                                                                  "key": "serverName"
                                                                },
                                                                {
                                                                  "key": "databaseName"
                                                                },
                                                                {
                                                                  "key": "extensionName"
                                                                }
                                                              ]
                                                            }
                                                          },
                                                          "status": "Accepted",
                                                          "code": 202,
                                                          "_postman_previewlanguage": "text",
                                                          "header": [],
                                                          "cookie": [],
                                                          "responseTime": null,
                                                          "body": null,
                                                          "createdAt": "2026-06-05T15:26:41.000Z",
                                                          "updatedAt": "2026-06-05T15:26:41.000Z",
                                                          "uid": "35240-271b3641-616e-45ed-9f8d-cd7851b2d46c"
                                                        }
                                                      ],
                                                      "createdAt": "2026-06-05T15:26:41.000Z",
                                                      "updatedAt": "2026-06-05T15:26:41.000Z",
                                                      "uid": "35240-974f93d5-6efd-4bcb-bc6c-380d12e40aa4"
                                                    }
                                                  ],
                                                  "id": "dc2020f3-4c5e-4b30-9a49-a013936c1016",
                                                  "createdAt": "2026-06-05T15:26:41.000Z",
                                                  "updatedAt": "2026-06-05T15:26:41.000Z",
                                                  "uid": "35240-dc2020f3-4c5e-4b30-9a49-a013936c1016"
                                                }
                                              ],
                                              "id": "3bcff18e-fbe3-491d-9d50-ea26037d263c",
                                              "createdAt": "2026-06-05T15:26:41.000Z",
                                              "updatedAt": "2026-06-05T15:26:41.000Z",
                                              "uid": "35240-3bcff18e-fbe3-491d-9d50-ea26037d263c"
                                            },
                                            {
                                              "name": "export",
                                              "item": [
                                                {
                                                  "name": "Microsoft Azure Post Subscriptions Subscriptionid Resourcegroups Resourcegroupname Providers Microsoft Sql Servers Servername Databases Databasename Export",
                                                  "id": "9f8a7cbf-6be7-4603-ad68-c58552505692",
                                                  "protocolProfileBehavior": {
                                                    "disableBodyPruning": true
                                                  },
                                                  "request": {
                                                    "method": "POST",
                                                    "header": [
                                                      {
                                                        "key": "Content-Type",
                                                        "value": "application/json"
                                                      },
                                                      {
                                                        "key": "Accept",
                                                        "value": "application/json"
                                                      }
                                                    ],
                                                    "body": {
                                                      "mode": "raw",
                                                      "raw": "{\n  \"storageKeyType\": \"StorageAccessKey\",\n  \"storageKey\": \"<string>\",\n  \"storageUri\": \"<string>\",\n  \"administratorLogin\": \"<string>\",\n  \"administratorLoginPassword\": \"<string>\",\n  \"authenticationType\": \"SQL\"\n}",
                                                      "options": {
                                                        "raw": {
                                                          "headerFamily": "json",
                                                          "language": "json"
                                                        }
                                                      }
                                                    },
                                                    "url": {
                                                      "raw": "{{baseUrl}}/subscriptions/:subscriptionId/resourceGroups/:resourceGroupName/providers/Microsoft.Sql/servers/:serverName/databases/:databaseName/export",
                                                      "host": [
                                                        "{{baseUrl}}"
                                                      ],
                                                      "path": [
                                                        "subscriptions",
                                                        ":subscriptionId",
                                                        "resourceGroups",
                                                        ":resourceGroupName",
                                                        "providers",
                                                        "Microsoft.Sql",
                                                        "servers",
                                                        ":serverName",
                                                        "databases",
                                                        ":databaseName",
                                                        "export"
                                                      ],
                                                      "variable": [
                                                        {
                                                          "id": "3462686d-a13c-46ff-b29b-24dea1d7e956",
                                                          "key": "subscriptionId"
                                                        },
                                                        {
                                                          "id": "cad8378e-8dbc-4b1b-b25e-5812332569bb",
                                                          "key": "resourceGroupName"
                                                        },
                                                        {
                                                          "id": "6596c56a-3048-43da-bee9-9aad9cd5484c",
                                                          "key": "serverName",
                                                          "value": "<string>",
                                                          "description": "(Required) The name of the server."
                                                        },
                                                        {
                                                          "id": "4a5e169b-3134-47ab-b214-0d2f3032c88b",
                                                          "key": "databaseName",
                                                          "value": "<string>",
                                                          "description": "(Required) The name of the database to be exported."
                                                        }
                                                      ]
                                                    },
                                                    "description": "Exports a database to a bacpac."
                                                  },
                                                  "response": [
                                                    {
                                                      "id": "7bad1bbb-04cd-4c60-8e81-34f279e2c98a",
                                                      "name": "OK",
                                                      "originalRequest": {
                                                        "method": "POST",
                                                        "header": [
                                                          {
                                                            "key": "Content-Type",
                                                            "value": "application/json"
                                                          },
                                                          {
                                                            "key": "Accept",
                                                            "value": "application/json"
                                                          }
                                                        ],
                                                        "body": {
                                                          "mode": "raw",
                                                          "raw": "{\n  \"storageKeyType\": \"StorageAccessKey\",\n  \"storageKey\": \"<string>\",\n  \"storageUri\": \"<string>\",\n  \"administratorLogin\": \"<string>\",\n  \"administratorLoginPassword\": \"<string>\",\n  \"authenticationType\": \"SQL\"\n}",
                                                          "options": {
                                                            "raw": {
                                                              "headerFamily": "json",
                                                              "language": "json"
                                                            }
                                                          }
                                                        },
                                                        "url": {
                                                          "raw": "{{baseUrl}}/subscriptions/:subscriptionId/resourceGroups/:resourceGroupName/providers/Microsoft.Sql/servers/:serverName/databases/:databaseName/export",
                                                          "host": [
                                                            "{{baseUrl}}"
                                                          ],
                                                          "path": [
                                                            "subscriptions",
                                                            ":subscriptionId",
                                                            "resourceGroups",
                                                            ":resourceGroupName",
                                                            "providers",
                                                            "Microsoft.Sql",
                                                            "servers",
                                                            ":serverName",
                                                            "databases",
                                                            ":databaseName",
                                                            "export"
                                                          ],
                                                          "variable": [
                                                            {
                                                              "key": "subscriptionId"
                                                            },
                                                            {
                                                              "key": "resourceGroupName"
                                                            },
                                                            {
                                                              "key": "serverName"
                                                            },
                                                            {
                                                              "key": "databaseName"
                                                            }
                                                          ]
                                                        }
                                                      },
                                                      "status": "OK",
                                                      "code": 200,
                                                      "_postman_previewlanguage": "json",
                                                      "header": [
                                                        {
                                                          "key": "Content-Type",
                                                          "value": "application/json"
                                                        }
                                                      ],
                                                      "cookie": [],
                                                      "responseTime": null,
                                                      "body": "{\n  \"properties\": {}\n}",
                                                      "createdAt": "2026-06-05T15:26:41.000Z",
                                                      "updatedAt": "2026-06-05T15:26:41.000Z",
                                                      "uid": "35240-7bad1bbb-04cd-4c60-8e81-34f279e2c98a"
                                                    },
                                                    {
                                                      "id": "34c18f64-24c5-4ded-85d8-a4e77a567779",
                                                      "name": "Accepted",
                                                      "originalRequest": {
                                                        "method": "POST",
                                                        "header": [
                                                          {
                                                            "key": "Content-Type",
                                                            "value": "application/json"
                                                          }
                                                        ],
                                                        "body": {
                                                          "mode": "raw",
                                                          "raw": "{\n  \"storageKeyType\": \"StorageAccessKey\",\n  \"storageKey\": \"<string>\",\n  \"storageUri\": \"<string>\",\n  \"administratorLogin\": \"<string>\",\n  \"administratorLoginPassword\": \"<string>\",\n  \"authenticationType\": \"SQL\"\n}",
                                                          "options": {
                                                            "raw": {
                                                              "headerFamily": "json",
                                                              "language": "json"
                                                            }
                                                          }
                                                        },
                                                        "url": {
                                                          "raw": "{{baseUrl}}/subscriptions/:subscriptionId/resourceGroups/:resourceGroupName/providers/Microsoft.Sql/servers/:serverName/databases/:databaseName/export",
                                                          "host": [
                                                            "{{baseUrl}}"
                                                          ],
                                                          "path": [
                                                            "subscriptions",
                                                            ":subscriptionId",
                                                            "resourceGroups",
                                                            ":resourceGroupName",
                                                            "providers",
                                                            "Microsoft.Sql",
                                                            "servers",
                                                            ":serverName",
                                                            "databases",
                                                            ":databaseName",
                                                            "export"
                                                          ],
                                                          "variable": [
                                                            {
                                                              "key": "subscriptionId"
                                                            },
                                                            {
                                                              "key": "resourceGroupName"
                                                            },
                                                            {
                                                              "key": "serverName"
                                                            },
                                                            {
                                                              "key": "databaseName"
                                                            }
                                                          ]
                                                        }
                                                      },
                                                      "status": "Accepted",
                                                      "code": 202,
                                                      "_postman_previewlanguage": "text",
                                                      "header": [],
                                                      "cookie": [],
                                                      "responseTime": null,
                                                      "body": null,
                                                      "createdAt": "2026-06-05T15:26:41.000Z",
                                                      "updatedAt": "2026-06-05T15:26:41.000Z",
                                                      "uid": "35240-34c18f64-24c5-4ded-85d8-a4e77a567779"
                                                    }
                                                  ],
                                                  "createdAt": "2026-06-05T15:26:41.000Z",
                                                  "updatedAt": "2026-06-05T15:26:41.000Z",
                                                  "uid": "35240-9f8a7cbf-6be7-4603-ad68-c58552505692"
                                                }
                                              ],
                                              "id": "0a095acb-4393-4ef9-8f3c-25d0e992f4fb",
                                              "createdAt": "2026-06-05T15:26:41.000Z",
                                              "updatedAt": "2026-06-05T15:26:41.000Z",
                                              "uid": "35240-0a095acb-4393-4ef9-8f3c-25d0e992f4fb"
                                            }
                                          ],
                                          "id": "e0bb9881-4c44-4e21-b11d-ec0e7bd8eb88",
                                          "createdAt": "2026-06-05T15:26:41.000Z",
                                          "updatedAt": "2026-06-05T15:26:41.000Z",
                                          "uid": "35240-e0bb9881-4c44-4e21-b11d-ec0e7bd8eb88"
                                        }
                                      ],
                                      "id": "21d14f1c-4a5a-4fb7-b713-426806048091",
                                      "createdAt": "2026-06-05T15:26:41.000Z",
                                      "updatedAt": "2026-06-05T15:26:41.000Z",
                                      "uid": "35240-21d14f1c-4a5a-4fb7-b713-426806048091"
                                    }
                                  ],
                                  "id": "2663eb2f-9497-43b7-b884-cddc7015e1be",
                                  "createdAt": "2026-06-05T15:26:41.000Z",
                                  "updatedAt": "2026-06-05T15:26:41.000Z",
                                  "uid": "35240-2663eb2f-9497-43b7-b884-cddc7015e1be"
                                }
                              ],
                              "id": "4a206504-3b65-474d-823e-bb875952a97d",
                              "createdAt": "2026-06-05T15:26:41.000Z",
                              "updatedAt": "2026-06-05T15:26:41.000Z",
                              "uid": "35240-4a206504-3b65-474d-823e-bb875952a97d"
                            }
                          ],
                          "id": "44673ef4-4691-4e98-9592-2bae2e9f676a",
                          "createdAt": "2026-06-05T15:26:41.000Z",
                          "updatedAt": "2026-06-05T15:26:41.000Z",
                          "uid": "35240-44673ef4-4691-4e98-9592-2bae2e9f676a"
                        }
                      ],
                      "id": "5134cdf8-47d0-4f8b-bf49-41a8eb50ed03",
                      "createdAt": "2026-06-05T15:26:41.000Z",
                      "updatedAt": "2026-06-05T15:26:41.000Z",
                      "uid": "35240-5134cdf8-47d0-4f8b-bf49-41a8eb50ed03"
                    }
                  ],
                  "id": "604d7983-56cf-4fb9-86f4-69e9e4f1950c",
                  "createdAt": "2026-06-05T15:26:41.000Z",
                  "updatedAt": "2026-06-05T15:26:41.000Z",
                  "uid": "35240-604d7983-56cf-4fb9-86f4-69e9e4f1950c"
                }
              ],
              "id": "79d3bf15-419b-4bee-b68c-c9cae0569f3f",
              "createdAt": "2026-06-05T15:26:41.000Z",
              "updatedAt": "2026-06-05T15:26:41.000Z",
              "uid": "35240-79d3bf15-419b-4bee-b68c-c9cae0569f3f"
            }
          ],
          "id": "09fee905-16f0-4f51-abc0-ea4f7f98ddec",
          "createdAt": "2026-06-05T15:26:41.000Z",
          "updatedAt": "2026-06-05T15:26:41.000Z",
          "uid": "35240-09fee905-16f0-4f51-abc0-ea4f7f98ddec"
        }
      ],
      "id": "97794f95-3ce7-45c6-a33e-4308aac65fc8",
      "createdAt": "2026-06-05T15:26:41.000Z",
      "updatedAt": "2026-06-05T15:26:41.000Z",
      "uid": "35240-97794f95-3ce7-45c6-a33e-4308aac65fc8"
    }
  ],
  "variable": [
    {
      "key": "baseUrl",
      "value": "https://management.azure.com"
    }
  ]
}