{
  "info": {
    "_postman_id": "92137b78-9f23-4e4c-b41e-a20658486e74",
    "name": "Microsoft Azure ContainerServiceAdminClient",
    "description": "Admin Container Service Management Client.",
    "schema": "https://schema.getpostman.com/json/collection/v2.1.0/collection.json",
    "createdAt": "2026-06-05T15:16:27.000Z",
    "updatedAt": "2026-06-05T15:16:27.000Z",
    "lastUpdatedBy": "35240",
    "uid": "35240-92137b78-9f23-4e4c-b41e-a20658486e74"
  },
  "item": [
    {
      "name": "subscriptions",
      "item": [
        {
          "name": "{subscriptionId}",
          "item": [
            {
              "name": "providers",
              "item": [
                {
                  "name": "Microsoft.ContainerService.Admin",
                  "item": [
                    {
                      "name": "locations",
                      "item": [
                        {
                          "name": "{location}",
                          "item": [
                            {
                              "name": "quotas",
                              "item": [
                                {
                                  "name": "Microsoft Azure Get Subscriptions Subscriptionid Providers Microsoft Containerservice Admin Locations Location Quotas",
                                  "id": "fd9296a5-6bda-458f-b780-8fa13eb1f08d",
                                  "protocolProfileBehavior": {
                                    "disableBodyPruning": true
                                  },
                                  "request": {
                                    "method": "GET",
                                    "header": [
                                      {
                                        "key": "Accept",
                                        "value": "application/json"
                                      }
                                    ],
                                    "url": {
                                      "raw": "{{baseUrl}}/subscriptions/:subscriptionId/providers/Microsoft.ContainerService.Admin/locations/:location/quotas",
                                      "host": [
                                        "{{baseUrl}}"
                                      ],
                                      "path": [
                                        "subscriptions",
                                        ":subscriptionId",
                                        "providers",
                                        "Microsoft.ContainerService.Admin",
                                        "locations",
                                        ":location",
                                        "quotas"
                                      ],
                                      "variable": [
                                        {
                                          "id": "6a214433-3249-47ea-8e2c-6de25f1ddfdf",
                                          "key": "subscriptionId"
                                        },
                                        {
                                          "id": "76b146c9-1f77-4d3c-8e5e-f479d1e08671",
                                          "key": "location"
                                        }
                                      ]
                                    },
                                    "description": "Returns a list of container service quotas at the given location."
                                  },
                                  "response": [
                                    {
                                      "id": "53daa4f9-4c99-40d8-86d9-f54d345232b2",
                                      "name": "OK -- The list of container service quotas has been returned.",
                                      "originalRequest": {
                                        "method": "GET",
                                        "header": [
                                          {
                                            "key": "Accept",
                                            "value": "application/json"
                                          },
                                          {
                                            "description": "Added as a part of security scheme: oauth2",
                                            "key": "Authorization",
                                            "value": "<token>"
                                          }
                                        ],
                                        "url": {
                                          "raw": "{{baseUrl}}/subscriptions/:subscriptionId/providers/Microsoft.ContainerService.Admin/locations/:location/quotas",
                                          "host": [
                                            "{{baseUrl}}"
                                          ],
                                          "path": [
                                            "subscriptions",
                                            ":subscriptionId",
                                            "providers",
                                            "Microsoft.ContainerService.Admin",
                                            "locations",
                                            ":location",
                                            "quotas"
                                          ],
                                          "variable": [
                                            {
                                              "key": "subscriptionId"
                                            },
                                            {
                                              "key": "location"
                                            }
                                          ]
                                        }
                                      },
                                      "status": "OK",
                                      "code": 200,
                                      "_postman_previewlanguage": "json",
                                      "header": [
                                        {
                                          "key": "Content-Type",
                                          "value": "application/json"
                                        }
                                      ],
                                      "cookie": [],
                                      "responseTime": null,
                                      "body": "{\n  \"value\": [\n    {\n      \"properties\": {}\n    },\n    {\n      \"properties\": {}\n    }\n  ],\n  \"nextLink\": \"<string>\"\n}",
                                      "createdAt": "2026-06-05T15:16:28.000Z",
                                      "updatedAt": "2026-06-05T15:16:28.000Z",
                                      "uid": "35240-53daa4f9-4c99-40d8-86d9-f54d345232b2"
                                    },
                                    {
                                      "id": "022cbd6a-803f-4e7d-b0bb-26feaf0952db",
                                      "name": "Error Response.",
                                      "originalRequest": {
                                        "method": "GET",
                                        "header": [
                                          {
                                            "key": "Accept",
                                            "value": "application/json"
                                          },
                                          {
                                            "description": "Added as a part of security scheme: oauth2",
                                            "key": "Authorization",
                                            "value": "<token>"
                                          }
                                        ],
                                        "url": {
                                          "raw": "{{baseUrl}}/subscriptions/:subscriptionId/providers/Microsoft.ContainerService.Admin/locations/:location/quotas",
                                          "host": [
                                            "{{baseUrl}}"
                                          ],
                                          "path": [
                                            "subscriptions",
                                            ":subscriptionId",
                                            "providers",
                                            "Microsoft.ContainerService.Admin",
                                            "locations",
                                            ":location",
                                            "quotas"
                                          ],
                                          "variable": [
                                            {
                                              "key": "subscriptionId"
                                            },
                                            {
                                              "key": "location"
                                            }
                                          ]
                                        }
                                      },
                                      "status": "Internal Server Error",
                                      "code": 500,
                                      "_postman_previewlanguage": "json",
                                      "header": [
                                        {
                                          "key": "Content-Type",
                                          "value": "application/json"
                                        }
                                      ],
                                      "cookie": [],
                                      "responseTime": null,
                                      "body": "{\n  \"value\": \"reference ../../../../../../common-types/resource-management/v2/types.json#/definitions/ErrorResponse not found in the OpenAPI spec\"\n}",
                                      "createdAt": "2026-06-05T15:16:28.000Z",
                                      "updatedAt": "2026-06-05T15:16:28.000Z",
                                      "uid": "35240-022cbd6a-803f-4e7d-b0bb-26feaf0952db"
                                    }
                                  ],
                                  "createdAt": "2026-06-05T15:16:28.000Z",
                                  "updatedAt": "2026-06-05T15:16:28.000Z",
                                  "uid": "35240-fd9296a5-6bda-458f-b780-8fa13eb1f08d"
                                }
                              ],
                              "id": "42a3677a-64c9-4d87-8072-6bf043e9b7d5",
                              "createdAt": "2026-06-05T15:16:28.000Z",
                              "updatedAt": "2026-06-05T15:16:28.000Z",
                              "uid": "35240-42a3677a-64c9-4d87-8072-6bf043e9b7d5"
                            }
                          ],
                          "id": "79f9db32-5771-4b1b-b3e5-6d409f28e206",
                          "createdAt": "2026-06-05T15:16:28.000Z",
                          "updatedAt": "2026-06-05T15:16:28.000Z",
                          "uid": "35240-79f9db32-5771-4b1b-b3e5-6d409f28e206"
                        }
                      ],
                      "id": "f83358f6-18bb-473a-93f2-ee91f055b738",
                      "createdAt": "2026-06-05T15:16:28.000Z",
                      "updatedAt": "2026-06-05T15:16:28.000Z",
                      "uid": "35240-f83358f6-18bb-473a-93f2-ee91f055b738"
                    }
                  ],
                  "id": "4f993ae7-7818-44a1-aa83-a94fd138abfd",
                  "createdAt": "2026-06-05T15:16:28.000Z",
                  "updatedAt": "2026-06-05T15:16:28.000Z",
                  "uid": "35240-4f993ae7-7818-44a1-aa83-a94fd138abfd"
                }
              ],
              "id": "759d517b-0d62-483d-b53c-f1a42d51d1f2",
              "createdAt": "2026-06-05T15:16:28.000Z",
              "updatedAt": "2026-06-05T15:16:28.000Z",
              "uid": "35240-759d517b-0d62-483d-b53c-f1a42d51d1f2"
            }
          ],
          "id": "a01c5c63-dbea-4e69-b49e-d9dab2f730f7",
          "createdAt": "2026-06-05T15:16:28.000Z",
          "updatedAt": "2026-06-05T15:16:28.000Z",
          "uid": "35240-a01c5c63-dbea-4e69-b49e-d9dab2f730f7"
        }
      ],
      "id": "2bb1f93d-a231-435e-a8d1-32322d3c0758",
      "createdAt": "2026-06-05T15:16:28.000Z",
      "updatedAt": "2026-06-05T15:16:28.000Z",
      "uid": "35240-2bb1f93d-a231-435e-a8d1-32322d3c0758"
    }
  ],
  "auth": {
    "type": "oauth2",
    "oauth2": [
      {
        "key": "scope",
        "value": "user_impersonation",
        "type": "string"
      },
      {
        "key": "authUrl",
        "value": "https://login.microsoftonline.com/common/oauth2/authorize",
        "type": "string"
      },
      {
        "key": "grant_type",
        "value": "implicit",
        "type": "string"
      }
    ]
  },
  "variable": [
    {
      "key": "baseUrl",
      "value": "https://management.azure.com"
    }
  ]
}