{
  "info": {
    "_postman_id": "72dc95eb-e7ff-430e-92b6-be686e0a4c6f",
    "name": "Microsoft Azure Guest Diagnostic Settings Association API",
    "description": "API to Add/Remove/List Guest Diagnostics Settings Association for Azure Resources",
    "schema": "https://schema.getpostman.com/json/collection/v2.1.0/collection.json",
    "createdAt": "2026-06-05T15:18:36.000Z",
    "updatedAt": "2026-06-05T15:18:36.000Z",
    "lastUpdatedBy": "35240",
    "uid": "35240-72dc95eb-e7ff-430e-92b6-be686e0a4c6f"
  },
  "item": [
    {
      "name": "{resourceUri}",
      "item": [
        {
          "name": "providers",
          "item": [
            {
              "name": "microsoft.insights",
              "item": [
                {
                  "name": "guestDiagnosticSettingsAssociation",
                  "item": [
                    {
                      "name": "{associationName}",
                      "item": [
                        {
                          "name": "Microsoft Azure Put Resourceuri Providers Microsoft Insights Guestdiagnosticsettingsassociation Associationname",
                          "id": "d895715e-600b-4e2f-b87b-cfa1e0952b3d",
                          "protocolProfileBehavior": {
                            "disableBodyPruning": true
                          },
                          "request": {
                            "method": "PUT",
                            "header": [
                              {
                                "key": "Content-Type",
                                "value": "application/json"
                              },
                              {
                                "key": "Accept",
                                "value": "application/json"
                              }
                            ],
                            "body": {
                              "mode": "raw",
                              "raw": "{\n  \"location\": \"<string>\",\n  \"properties\": {},\n  \"id\": \"<string>\",\n  \"name\": \"<string>\",\n  \"type\": \"<string>\",\n  \"tags\": {\n    \"incididuntb6\": \"<string>\",\n    \"elita8\": \"<string>\"\n  }\n}",
                              "options": {
                                "raw": {
                                  "headerFamily": "json",
                                  "language": "json"
                                }
                              }
                            },
                            "url": {
                              "raw": "{{baseUrl}}/:resourceUri/providers/microsoft.insights/guestDiagnosticSettingsAssociation/:associationName",
                              "host": [
                                "{{baseUrl}}"
                              ],
                              "path": [
                                ":resourceUri",
                                "providers",
                                "microsoft.insights",
                                "guestDiagnosticSettingsAssociation",
                                ":associationName"
                              ],
                              "variable": [
                                {
                                  "id": "da9ebcb8-ac71-4158-9ef9-5a51c157b9e9",
                                  "key": "resourceUri",
                                  "value": "<string>",
                                  "description": "(Required) The fully qualified ID of the resource, including the resource name and resource type."
                                },
                                {
                                  "id": "4bc5fa69-cfa8-4cbd-ad4c-3af821b59ec8",
                                  "key": "associationName",
                                  "value": "<string>",
                                  "description": "(Required) The name of the diagnostic settings association."
                                }
                              ]
                            },
                            "description": "Creates or updates guest diagnostics settings association."
                          },
                          "response": [
                            {
                              "id": "9138f67c-f62a-495c-bb81-dad10bf4fc2d",
                              "name": "An existing guest diagnostic settings association was successfully updated.",
                              "originalRequest": {
                                "method": "PUT",
                                "header": [
                                  {
                                    "key": "Content-Type",
                                    "value": "application/json"
                                  },
                                  {
                                    "key": "Accept",
                                    "value": "application/json"
                                  },
                                  {
                                    "description": "Added as a part of security scheme: oauth2",
                                    "key": "Authorization",
                                    "value": "<token>"
                                  }
                                ],
                                "body": {
                                  "mode": "raw",
                                  "raw": "{\n  \"location\": \"<string>\",\n  \"properties\": {},\n  \"id\": \"<string>\",\n  \"name\": \"<string>\",\n  \"type\": \"<string>\",\n  \"tags\": {\n    \"incididuntb6\": \"<string>\",\n    \"elita8\": \"<string>\"\n  }\n}",
                                  "options": {
                                    "raw": {
                                      "headerFamily": "json",
                                      "language": "json"
                                    }
                                  }
                                },
                                "url": {
                                  "raw": "{{baseUrl}}/:resourceUri/providers/microsoft.insights/guestDiagnosticSettingsAssociation/:associationName",
                                  "host": [
                                    "{{baseUrl}}"
                                  ],
                                  "path": [
                                    ":resourceUri",
                                    "providers",
                                    "microsoft.insights",
                                    "guestDiagnosticSettingsAssociation",
                                    ":associationName"
                                  ],
                                  "variable": [
                                    {
                                      "key": "resourceUri"
                                    },
                                    {
                                      "key": "associationName"
                                    }
                                  ]
                                }
                              },
                              "status": "OK",
                              "code": 200,
                              "_postman_previewlanguage": "json",
                              "header": [
                                {
                                  "key": "Content-Type",
                                  "value": "application/json"
                                }
                              ],
                              "cookie": [],
                              "responseTime": null,
                              "body": "{\n  \"location\": \"<string>\",\n  \"properties\": {},\n  \"id\": \"<string>\",\n  \"name\": \"<string>\",\n  \"type\": \"<string>\",\n  \"tags\": {\n    \"incididuntb6\": \"<string>\",\n    \"elita8\": \"<string>\"\n  }\n}",
                              "createdAt": "2026-06-05T15:18:36.000Z",
                              "updatedAt": "2026-06-05T15:18:36.000Z",
                              "uid": "35240-9138f67c-f62a-495c-bb81-dad10bf4fc2d"
                            },
                            {
                              "id": "7cb18b96-b336-4297-8209-1ce6286564a4",
                              "name": "A new guest diagnostic settings association was successfully created.",
                              "originalRequest": {
                                "method": "PUT",
                                "header": [
                                  {
                                    "key": "Content-Type",
                                    "value": "application/json"
                                  },
                                  {
                                    "key": "Accept",
                                    "value": "application/json"
                                  },
                                  {
                                    "description": "Added as a part of security scheme: oauth2",
                                    "key": "Authorization",
                                    "value": "<token>"
                                  }
                                ],
                                "body": {
                                  "mode": "raw",
                                  "raw": "{\n  \"location\": \"<string>\",\n  \"properties\": {},\n  \"id\": \"<string>\",\n  \"name\": \"<string>\",\n  \"type\": \"<string>\",\n  \"tags\": {\n    \"incididuntb6\": \"<string>\",\n    \"elita8\": \"<string>\"\n  }\n}",
                                  "options": {
                                    "raw": {
                                      "headerFamily": "json",
                                      "language": "json"
                                    }
                                  }
                                },
                                "url": {
                                  "raw": "{{baseUrl}}/:resourceUri/providers/microsoft.insights/guestDiagnosticSettingsAssociation/:associationName",
                                  "host": [
                                    "{{baseUrl}}"
                                  ],
                                  "path": [
                                    ":resourceUri",
                                    "providers",
                                    "microsoft.insights",
                                    "guestDiagnosticSettingsAssociation",
                                    ":associationName"
                                  ],
                                  "variable": [
                                    {
                                      "key": "resourceUri"
                                    },
                                    {
                                      "key": "associationName"
                                    }
                                  ]
                                }
                              },
                              "status": "Created",
                              "code": 201,
                              "_postman_previewlanguage": "json",
                              "header": [
                                {
                                  "key": "Content-Type",
                                  "value": "application/json"
                                }
                              ],
                              "cookie": [],
                              "responseTime": null,
                              "body": "{\n  \"location\": \"<string>\",\n  \"properties\": {},\n  \"id\": \"<string>\",\n  \"name\": \"<string>\",\n  \"type\": \"<string>\",\n  \"tags\": {\n    \"incididuntb6\": \"<string>\",\n    \"elita8\": \"<string>\"\n  }\n}",
                              "createdAt": "2026-06-05T15:18:36.000Z",
                              "updatedAt": "2026-06-05T15:18:36.000Z",
                              "uid": "35240-7cb18b96-b336-4297-8209-1ce6286564a4"
                            },
                            {
                              "id": "ccb3e4a1-6ad3-40ae-bf62-b3f06611e728",
                              "name": "An error occurred and the guest diagnostic settings association could not be created or updated.",
                              "originalRequest": {
                                "method": "PUT",
                                "header": [
                                  {
                                    "key": "Content-Type",
                                    "value": "application/json"
                                  },
                                  {
                                    "key": "Accept",
                                    "value": "application/json"
                                  },
                                  {
                                    "description": "Added as a part of security scheme: oauth2",
                                    "key": "Authorization",
                                    "value": "<token>"
                                  }
                                ],
                                "body": {
                                  "mode": "raw",
                                  "raw": "{\n  \"location\": \"<string>\",\n  \"properties\": {},\n  \"id\": \"<string>\",\n  \"name\": \"<string>\",\n  \"type\": \"<string>\",\n  \"tags\": {\n    \"incididuntb6\": \"<string>\",\n    \"elita8\": \"<string>\"\n  }\n}",
                                  "options": {
                                    "raw": {
                                      "headerFamily": "json",
                                      "language": "json"
                                    }
                                  }
                                },
                                "url": {
                                  "raw": "{{baseUrl}}/:resourceUri/providers/microsoft.insights/guestDiagnosticSettingsAssociation/:associationName",
                                  "host": [
                                    "{{baseUrl}}"
                                  ],
                                  "path": [
                                    ":resourceUri",
                                    "providers",
                                    "microsoft.insights",
                                    "guestDiagnosticSettingsAssociation",
                                    ":associationName"
                                  ],
                                  "variable": [
                                    {
                                      "key": "resourceUri"
                                    },
                                    {
                                      "key": "associationName"
                                    }
                                  ]
                                }
                              },
                              "status": "Internal Server Error",
                              "code": 500,
                              "_postman_previewlanguage": "json",
                              "header": [
                                {
                                  "key": "Content-Type",
                                  "value": "application/json"
                                }
                              ],
                              "cookie": [],
                              "responseTime": null,
                              "body": "{\n  \"code\": \"<string>\",\n  \"message\": \"<string>\"\n}",
                              "createdAt": "2026-06-05T15:18:36.000Z",
                              "updatedAt": "2026-06-05T15:18:36.000Z",
                              "uid": "35240-ccb3e4a1-6ad3-40ae-bf62-b3f06611e728"
                            }
                          ],
                          "createdAt": "2026-06-05T15:18:36.000Z",
                          "updatedAt": "2026-06-05T15:18:36.000Z",
                          "uid": "35240-d895715e-600b-4e2f-b87b-cfa1e0952b3d"
                        },
                        {
                          "name": "Microsoft Azure Get Resourceuri Providers Microsoft Insights Guestdiagnosticsettingsassociation Associationname",
                          "id": "4756d9ba-f715-42f7-9d11-80f2c0df601a",
                          "protocolProfileBehavior": {
                            "disableBodyPruning": true
                          },
                          "request": {
                            "method": "GET",
                            "header": [
                              {
                                "key": "Accept",
                                "value": "application/json"
                              }
                            ],
                            "url": {
                              "raw": "{{baseUrl}}/:resourceUri/providers/microsoft.insights/guestDiagnosticSettingsAssociation/:associationName",
                              "host": [
                                "{{baseUrl}}"
                              ],
                              "path": [
                                ":resourceUri",
                                "providers",
                                "microsoft.insights",
                                "guestDiagnosticSettingsAssociation",
                                ":associationName"
                              ],
                              "variable": [
                                {
                                  "id": "c2acfd64-2fd1-4103-b444-1513e9e50f11",
                                  "key": "resourceUri",
                                  "value": "<string>",
                                  "description": "(Required) The fully qualified ID of the resource, including the resource name and resource type."
                                },
                                {
                                  "id": "26b161d3-a58a-417e-863a-0a79a8aa76d5",
                                  "key": "associationName",
                                  "value": "<string>",
                                  "description": "(Required) The name of the diagnostic settings association."
                                }
                              ]
                            },
                            "description": "Gets guest diagnostics association settings."
                          },
                          "response": [
                            {
                              "id": "52a316e0-440e-421b-bcd9-1f876de95c79",
                              "name": "The request succeeded.",
                              "originalRequest": {
                                "method": "GET",
                                "header": [
                                  {
                                    "key": "Accept",
                                    "value": "application/json"
                                  },
                                  {
                                    "description": "Added as a part of security scheme: oauth2",
                                    "key": "Authorization",
                                    "value": "<token>"
                                  }
                                ],
                                "url": {
                                  "raw": "{{baseUrl}}/:resourceUri/providers/microsoft.insights/guestDiagnosticSettingsAssociation/:associationName",
                                  "host": [
                                    "{{baseUrl}}"
                                  ],
                                  "path": [
                                    ":resourceUri",
                                    "providers",
                                    "microsoft.insights",
                                    "guestDiagnosticSettingsAssociation",
                                    ":associationName"
                                  ],
                                  "variable": [
                                    {
                                      "key": "resourceUri"
                                    },
                                    {
                                      "key": "associationName"
                                    }
                                  ]
                                }
                              },
                              "status": "OK",
                              "code": 200,
                              "_postman_previewlanguage": "json",
                              "header": [
                                {
                                  "key": "Content-Type",
                                  "value": "application/json"
                                }
                              ],
                              "cookie": [],
                              "responseTime": null,
                              "body": "{\n  \"location\": \"<string>\",\n  \"properties\": {},\n  \"id\": \"<string>\",\n  \"name\": \"<string>\",\n  \"type\": \"<string>\",\n  \"tags\": {\n    \"incididuntb6\": \"<string>\",\n    \"elita8\": \"<string>\"\n  }\n}",
                              "createdAt": "2026-06-05T15:18:36.000Z",
                              "updatedAt": "2026-06-05T15:18:36.000Z",
                              "uid": "35240-52a316e0-440e-421b-bcd9-1f876de95c79"
                            },
                            {
                              "id": "2f542691-83fd-4bb9-b743-371ccd07139c",
                              "name": "An error occurred and the diagnostic settings association could not be retrieved.",
                              "originalRequest": {
                                "method": "GET",
                                "header": [
                                  {
                                    "key": "Accept",
                                    "value": "application/json"
                                  },
                                  {
                                    "description": "Added as a part of security scheme: oauth2",
                                    "key": "Authorization",
                                    "value": "<token>"
                                  }
                                ],
                                "url": {
                                  "raw": "{{baseUrl}}/:resourceUri/providers/microsoft.insights/guestDiagnosticSettingsAssociation/:associationName",
                                  "host": [
                                    "{{baseUrl}}"
                                  ],
                                  "path": [
                                    ":resourceUri",
                                    "providers",
                                    "microsoft.insights",
                                    "guestDiagnosticSettingsAssociation",
                                    ":associationName"
                                  ],
                                  "variable": [
                                    {
                                      "key": "resourceUri"
                                    },
                                    {
                                      "key": "associationName"
                                    }
                                  ]
                                }
                              },
                              "status": "Internal Server Error",
                              "code": 500,
                              "_postman_previewlanguage": "json",
                              "header": [
                                {
                                  "key": "Content-Type",
                                  "value": "application/json"
                                }
                              ],
                              "cookie": [],
                              "responseTime": null,
                              "body": "{\n  \"code\": \"<string>\",\n  \"message\": \"<string>\"\n}",
                              "createdAt": "2026-06-05T15:18:36.000Z",
                              "updatedAt": "2026-06-05T15:18:36.000Z",
                              "uid": "35240-2f542691-83fd-4bb9-b743-371ccd07139c"
                            }
                          ],
                          "createdAt": "2026-06-05T15:18:36.000Z",
                          "updatedAt": "2026-06-05T15:18:36.000Z",
                          "uid": "35240-4756d9ba-f715-42f7-9d11-80f2c0df601a"
                        },
                        {
                          "name": "Microsoft Azure Delete Resourceuri Providers Microsoft Insights Guestdiagnosticsettingsassociation Associationname",
                          "id": "91fc13af-7b80-4c20-9302-ab2b078d6a7e",
                          "protocolProfileBehavior": {
                            "disableBodyPruning": true
                          },
                          "request": {
                            "method": "DELETE",
                            "header": [
                              {
                                "key": "Accept",
                                "value": "application/json"
                              }
                            ],
                            "url": {
                              "raw": "{{baseUrl}}/:resourceUri/providers/microsoft.insights/guestDiagnosticSettingsAssociation/:associationName",
                              "host": [
                                "{{baseUrl}}"
                              ],
                              "path": [
                                ":resourceUri",
                                "providers",
                                "microsoft.insights",
                                "guestDiagnosticSettingsAssociation",
                                ":associationName"
                              ],
                              "variable": [
                                {
                                  "id": "3a7e5fb8-d039-437d-bac2-edde4f7d30ca",
                                  "key": "resourceUri",
                                  "value": "<string>",
                                  "description": "(Required) The fully qualified ID of the resource, including the resource name and resource type."
                                },
                                {
                                  "id": "3068f091-ba62-4fd1-9592-eb0054f76dfa",
                                  "key": "associationName",
                                  "value": "<string>",
                                  "description": "(Required) The name of the diagnostic settings association."
                                }
                              ]
                            },
                            "description": "Delete guest diagnostics association settings."
                          },
                          "response": [
                            {
                              "id": "ae5af51a-cd9e-4748-9f94-aca89aac6308",
                              "name": "The diagnostic settings association was successfully deleted.",
                              "originalRequest": {
                                "method": "DELETE",
                                "header": [
                                  {
                                    "description": "Added as a part of security scheme: oauth2",
                                    "key": "Authorization",
                                    "value": "<token>"
                                  }
                                ],
                                "url": {
                                  "raw": "{{baseUrl}}/:resourceUri/providers/microsoft.insights/guestDiagnosticSettingsAssociation/:associationName",
                                  "host": [
                                    "{{baseUrl}}"
                                  ],
                                  "path": [
                                    ":resourceUri",
                                    "providers",
                                    "microsoft.insights",
                                    "guestDiagnosticSettingsAssociation",
                                    ":associationName"
                                  ],
                                  "variable": [
                                    {
                                      "key": "resourceUri"
                                    },
                                    {
                                      "key": "associationName"
                                    }
                                  ]
                                }
                              },
                              "status": "OK",
                              "code": 200,
                              "_postman_previewlanguage": "text",
                              "header": [],
                              "cookie": [],
                              "responseTime": null,
                              "body": null,
                              "createdAt": "2026-06-05T15:18:36.000Z",
                              "updatedAt": "2026-06-05T15:18:36.000Z",
                              "uid": "35240-ae5af51a-cd9e-4748-9f94-aca89aac6308"
                            },
                            {
                              "id": "b68879df-4f3c-4dba-ad41-07cc16ccf0aa",
                              "name": "The diagnostic settings association does not exist. It may have already been deleted.",
                              "originalRequest": {
                                "method": "DELETE",
                                "header": [
                                  {
                                    "description": "Added as a part of security scheme: oauth2",
                                    "key": "Authorization",
                                    "value": "<token>"
                                  }
                                ],
                                "url": {
                                  "raw": "{{baseUrl}}/:resourceUri/providers/microsoft.insights/guestDiagnosticSettingsAssociation/:associationName",
                                  "host": [
                                    "{{baseUrl}}"
                                  ],
                                  "path": [
                                    ":resourceUri",
                                    "providers",
                                    "microsoft.insights",
                                    "guestDiagnosticSettingsAssociation",
                                    ":associationName"
                                  ],
                                  "variable": [
                                    {
                                      "key": "resourceUri"
                                    },
                                    {
                                      "key": "associationName"
                                    }
                                  ]
                                }
                              },
                              "status": "No Content",
                              "code": 204,
                              "_postman_previewlanguage": "text",
                              "header": [],
                              "cookie": [],
                              "responseTime": null,
                              "body": null,
                              "createdAt": "2026-06-05T15:18:36.000Z",
                              "updatedAt": "2026-06-05T15:18:36.000Z",
                              "uid": "35240-b68879df-4f3c-4dba-ad41-07cc16ccf0aa"
                            },
                            {
                              "id": "835a3e40-9427-4ac8-88b3-a7a598184ddd",
                              "name": "An error occurred and the diagnostic settings association could not be deleted.",
                              "originalRequest": {
                                "method": "DELETE",
                                "header": [
                                  {
                                    "key": "Accept",
                                    "value": "application/json"
                                  },
                                  {
                                    "description": "Added as a part of security scheme: oauth2",
                                    "key": "Authorization",
                                    "value": "<token>"
                                  }
                                ],
                                "url": {
                                  "raw": "{{baseUrl}}/:resourceUri/providers/microsoft.insights/guestDiagnosticSettingsAssociation/:associationName",
                                  "host": [
                                    "{{baseUrl}}"
                                  ],
                                  "path": [
                                    ":resourceUri",
                                    "providers",
                                    "microsoft.insights",
                                    "guestDiagnosticSettingsAssociation",
                                    ":associationName"
                                  ],
                                  "variable": [
                                    {
                                      "key": "resourceUri"
                                    },
                                    {
                                      "key": "associationName"
                                    }
                                  ]
                                }
                              },
                              "status": "Internal Server Error",
                              "code": 500,
                              "_postman_previewlanguage": "json",
                              "header": [
                                {
                                  "key": "Content-Type",
                                  "value": "application/json"
                                }
                              ],
                              "cookie": [],
                              "responseTime": null,
                              "body": "{\n  \"code\": \"<string>\",\n  \"message\": \"<string>\"\n}",
                              "createdAt": "2026-06-05T15:18:36.000Z",
                              "updatedAt": "2026-06-05T15:18:36.000Z",
                              "uid": "35240-835a3e40-9427-4ac8-88b3-a7a598184ddd"
                            }
                          ],
                          "createdAt": "2026-06-05T15:18:36.000Z",
                          "updatedAt": "2026-06-05T15:18:36.000Z",
                          "uid": "35240-91fc13af-7b80-4c20-9302-ab2b078d6a7e"
                        },
                        {
                          "name": "Microsoft Azure Patch Resourceuri Providers Microsoft Insights Guestdiagnosticsettingsassociation Associationname",
                          "id": "02d07b68-51cf-4189-9be3-5023fc010c0a",
                          "protocolProfileBehavior": {
                            "disableBodyPruning": true
                          },
                          "request": {
                            "method": "PATCH",
                            "header": [
                              {
                                "key": "Content-Type",
                                "value": "application/json"
                              },
                              {
                                "key": "Accept",
                                "value": "application/json"
                              }
                            ],
                            "body": {
                              "mode": "raw",
                              "raw": "{\n  \"tags\": {\n    \"est_4b9\": \"<string>\"\n  },\n  \"properties\": {\n    \"guestDiagnosticSettingsName\": \"<string>\"\n  }\n}",
                              "options": {
                                "raw": {
                                  "headerFamily": "json",
                                  "language": "json"
                                }
                              }
                            },
                            "url": {
                              "raw": "{{baseUrl}}/:resourceUri/providers/microsoft.insights/guestDiagnosticSettingsAssociation/:associationName",
                              "host": [
                                "{{baseUrl}}"
                              ],
                              "path": [
                                ":resourceUri",
                                "providers",
                                "microsoft.insights",
                                "guestDiagnosticSettingsAssociation",
                                ":associationName"
                              ],
                              "variable": [
                                {
                                  "id": "6e85fd15-23dd-4543-93d6-bbbe6e3d7a15",
                                  "key": "resourceUri",
                                  "value": "<string>",
                                  "description": "(Required) The fully qualified ID of the resource, including the resource name and resource type."
                                },
                                {
                                  "id": "3d567957-2c58-47cb-96d0-3c52dc8769f8",
                                  "key": "associationName",
                                  "value": "<string>",
                                  "description": "(Required) The name of the diagnostic settings association."
                                }
                              ]
                            },
                            "description": "Updates an existing guestDiagnosticsSettingsAssociation Resource. To update other fields use the CreateOrUpdate method"
                          },
                          "response": [
                            {
                              "id": "77ffdc74-0ddf-4661-9534-30038b3d036c",
                              "name": "An existing guest diagnostics setting resource was successfully updated.",
                              "originalRequest": {
                                "method": "PATCH",
                                "header": [
                                  {
                                    "key": "Content-Type",
                                    "value": "application/json"
                                  },
                                  {
                                    "key": "Accept",
                                    "value": "application/json"
                                  },
                                  {
                                    "description": "Added as a part of security scheme: oauth2",
                                    "key": "Authorization",
                                    "value": "<token>"
                                  }
                                ],
                                "body": {
                                  "mode": "raw",
                                  "raw": "{\n  \"tags\": {\n    \"est_4b9\": \"<string>\"\n  },\n  \"properties\": {\n    \"guestDiagnosticSettingsName\": \"<string>\"\n  }\n}",
                                  "options": {
                                    "raw": {
                                      "headerFamily": "json",
                                      "language": "json"
                                    }
                                  }
                                },
                                "url": {
                                  "raw": "{{baseUrl}}/:resourceUri/providers/microsoft.insights/guestDiagnosticSettingsAssociation/:associationName",
                                  "host": [
                                    "{{baseUrl}}"
                                  ],
                                  "path": [
                                    ":resourceUri",
                                    "providers",
                                    "microsoft.insights",
                                    "guestDiagnosticSettingsAssociation",
                                    ":associationName"
                                  ],
                                  "variable": [
                                    {
                                      "key": "resourceUri"
                                    },
                                    {
                                      "key": "associationName"
                                    }
                                  ]
                                }
                              },
                              "status": "OK",
                              "code": 200,
                              "_postman_previewlanguage": "json",
                              "header": [
                                {
                                  "key": "Content-Type",
                                  "value": "application/json"
                                }
                              ],
                              "cookie": [],
                              "responseTime": null,
                              "body": "{\n  \"location\": \"<string>\",\n  \"properties\": {},\n  \"id\": \"<string>\",\n  \"name\": \"<string>\",\n  \"type\": \"<string>\",\n  \"tags\": {\n    \"incididuntb6\": \"<string>\",\n    \"elita8\": \"<string>\"\n  }\n}",
                              "createdAt": "2026-06-05T15:18:36.000Z",
                              "updatedAt": "2026-06-05T15:18:36.000Z",
                              "uid": "35240-77ffdc74-0ddf-4661-9534-30038b3d036c"
                            },
                            {
                              "id": "468ad673-5095-4808-bb94-bfd7dda03ae4",
                              "name": "Error response describing why the operation failed.",
                              "originalRequest": {
                                "method": "PATCH",
                                "header": [
                                  {
                                    "key": "Content-Type",
                                    "value": "application/json"
                                  },
                                  {
                                    "key": "Accept",
                                    "value": "application/json"
                                  },
                                  {
                                    "description": "Added as a part of security scheme: oauth2",
                                    "key": "Authorization",
                                    "value": "<token>"
                                  }
                                ],
                                "body": {
                                  "mode": "raw",
                                  "raw": "{\n  \"tags\": {\n    \"est_4b9\": \"<string>\"\n  },\n  \"properties\": {\n    \"guestDiagnosticSettingsName\": \"<string>\"\n  }\n}",
                                  "options": {
                                    "raw": {
                                      "headerFamily": "json",
                                      "language": "json"
                                    }
                                  }
                                },
                                "url": {
                                  "raw": "{{baseUrl}}/:resourceUri/providers/microsoft.insights/guestDiagnosticSettingsAssociation/:associationName",
                                  "host": [
                                    "{{baseUrl}}"
                                  ],
                                  "path": [
                                    ":resourceUri",
                                    "providers",
                                    "microsoft.insights",
                                    "guestDiagnosticSettingsAssociation",
                                    ":associationName"
                                  ],
                                  "variable": [
                                    {
                                      "key": "resourceUri"
                                    },
                                    {
                                      "key": "associationName"
                                    }
                                  ]
                                }
                              },
                              "status": "Internal Server Error",
                              "code": 500,
                              "_postman_previewlanguage": "json",
                              "header": [
                                {
                                  "key": "Content-Type",
                                  "value": "application/json"
                                }
                              ],
                              "cookie": [],
                              "responseTime": null,
                              "body": "{\n  \"code\": \"<string>\",\n  \"message\": \"<string>\"\n}",
                              "createdAt": "2026-06-05T15:18:36.000Z",
                              "updatedAt": "2026-06-05T15:18:36.000Z",
                              "uid": "35240-468ad673-5095-4808-bb94-bfd7dda03ae4"
                            }
                          ],
                          "createdAt": "2026-06-05T15:18:36.000Z",
                          "updatedAt": "2026-06-05T15:18:36.000Z",
                          "uid": "35240-02d07b68-51cf-4189-9be3-5023fc010c0a"
                        }
                      ],
                      "id": "1020a55e-c829-48e5-bb35-6fc9a5a3d2ed",
                      "createdAt": "2026-06-05T15:18:36.000Z",
                      "updatedAt": "2026-06-05T15:18:36.000Z",
                      "uid": "35240-1020a55e-c829-48e5-bb35-6fc9a5a3d2ed"
                    }
                  ],
                  "id": "55e00da5-9e89-4eaf-bfa4-5f77f423c420",
                  "createdAt": "2026-06-05T15:18:36.000Z",
                  "updatedAt": "2026-06-05T15:18:36.000Z",
                  "uid": "35240-55e00da5-9e89-4eaf-bfa4-5f77f423c420"
                }
              ],
              "id": "de857ccb-f713-470d-a6fa-142d7aed9847",
              "createdAt": "2026-06-05T15:18:36.000Z",
              "updatedAt": "2026-06-05T15:18:36.000Z",
              "uid": "35240-de857ccb-f713-470d-a6fa-142d7aed9847"
            }
          ],
          "id": "c3aae32d-6f8c-470f-8add-8dd2c8f2b143",
          "createdAt": "2026-06-05T15:18:36.000Z",
          "updatedAt": "2026-06-05T15:18:36.000Z",
          "uid": "35240-c3aae32d-6f8c-470f-8add-8dd2c8f2b143"
        }
      ],
      "id": "0f1146aa-3e55-4180-bc4e-1c564c426021",
      "createdAt": "2026-06-05T15:18:36.000Z",
      "updatedAt": "2026-06-05T15:18:36.000Z",
      "uid": "35240-0f1146aa-3e55-4180-bc4e-1c564c426021"
    },
    {
      "name": "subscriptions",
      "item": [
        {
          "name": "{subscriptionId}",
          "item": [
            {
              "name": "providers",
              "item": [
                {
                  "name": "microsoft.insights",
                  "item": [
                    {
                      "name": "guestDiagnosticSettingsAssociations",
                      "item": [
                        {
                          "name": "Microsoft Azure Get Subscriptions Subscriptionid Providers Microsoft Insights Guestdiagnosticsettingsassociations",
                          "id": "6a4a5a2b-69c8-48a2-bacb-81e679456bb1",
                          "protocolProfileBehavior": {
                            "disableBodyPruning": true
                          },
                          "request": {
                            "method": "GET",
                            "header": [
                              {
                                "key": "Accept",
                                "value": "application/json"
                              }
                            ],
                            "url": {
                              "raw": "{{baseUrl}}/subscriptions/:subscriptionId/providers/microsoft.insights/guestDiagnosticSettingsAssociations",
                              "host": [
                                "{{baseUrl}}"
                              ],
                              "path": [
                                "subscriptions",
                                ":subscriptionId",
                                "providers",
                                "microsoft.insights",
                                "guestDiagnosticSettingsAssociations"
                              ],
                              "variable": [
                                {
                                  "id": "109dc37c-5b34-4a9b-9b7c-5617c930449f",
                                  "key": "subscriptionId"
                                }
                              ]
                            },
                            "description": "Get a list of all guest diagnostic settings association in a subscription."
                          },
                          "response": [
                            {
                              "id": "488664b2-eb28-466e-bfc9-4fc712ef58bb",
                              "name": "The request succeeded.",
                              "originalRequest": {
                                "method": "GET",
                                "header": [
                                  {
                                    "key": "Accept",
                                    "value": "application/json"
                                  },
                                  {
                                    "description": "Added as a part of security scheme: oauth2",
                                    "key": "Authorization",
                                    "value": "<token>"
                                  }
                                ],
                                "url": {
                                  "raw": "{{baseUrl}}/subscriptions/:subscriptionId/providers/microsoft.insights/guestDiagnosticSettingsAssociations",
                                  "host": [
                                    "{{baseUrl}}"
                                  ],
                                  "path": [
                                    "subscriptions",
                                    ":subscriptionId",
                                    "providers",
                                    "microsoft.insights",
                                    "guestDiagnosticSettingsAssociations"
                                  ],
                                  "variable": [
                                    {
                                      "key": "subscriptionId"
                                    }
                                  ]
                                }
                              },
                              "status": "OK",
                              "code": 200,
                              "_postman_previewlanguage": "json",
                              "header": [
                                {
                                  "key": "Content-Type",
                                  "value": "application/json"
                                }
                              ],
                              "cookie": [],
                              "responseTime": null,
                              "body": "{\n  \"value\": [\n    {\n      \"location\": \"<string>\",\n      \"properties\": {},\n      \"id\": \"<string>\",\n      \"name\": \"<string>\",\n      \"type\": \"<string>\",\n      \"tags\": {\n        \"Duis_4ce\": \"<string>\",\n        \"eaa2\": \"<string>\"\n      }\n    },\n    {\n      \"location\": \"<string>\",\n      \"properties\": {},\n      \"id\": \"<string>\",\n      \"name\": \"<string>\",\n      \"type\": \"<string>\",\n      \"tags\": {\n        \"ametb\": \"<string>\",\n        \"consequat_8\": \"<string>\",\n        \"Excepteur_de\": \"<string>\"\n      }\n    }\n  ],\n  \"nextLink\": \"<string>\"\n}",
                              "createdAt": "2026-06-05T15:18:36.000Z",
                              "updatedAt": "2026-06-05T15:18:36.000Z",
                              "uid": "35240-488664b2-eb28-466e-bfc9-4fc712ef58bb"
                            },
                            {
                              "id": "223fc079-2729-4445-855d-b7becf45b8f5",
                              "name": "An error occurred and the list of guest diagnostic settings association could not be retrieved.",
                              "originalRequest": {
                                "method": "GET",
                                "header": [
                                  {
                                    "key": "Accept",
                                    "value": "application/json"
                                  },
                                  {
                                    "description": "Added as a part of security scheme: oauth2",
                                    "key": "Authorization",
                                    "value": "<token>"
                                  }
                                ],
                                "url": {
                                  "raw": "{{baseUrl}}/subscriptions/:subscriptionId/providers/microsoft.insights/guestDiagnosticSettingsAssociations",
                                  "host": [
                                    "{{baseUrl}}"
                                  ],
                                  "path": [
                                    "subscriptions",
                                    ":subscriptionId",
                                    "providers",
                                    "microsoft.insights",
                                    "guestDiagnosticSettingsAssociations"
                                  ],
                                  "variable": [
                                    {
                                      "key": "subscriptionId"
                                    }
                                  ]
                                }
                              },
                              "status": "Internal Server Error",
                              "code": 500,
                              "_postman_previewlanguage": "json",
                              "header": [
                                {
                                  "key": "Content-Type",
                                  "value": "application/json"
                                }
                              ],
                              "cookie": [],
                              "responseTime": null,
                              "body": "{\n  \"code\": \"<string>\",\n  \"message\": \"<string>\"\n}",
                              "createdAt": "2026-06-05T15:18:36.000Z",
                              "updatedAt": "2026-06-05T15:18:36.000Z",
                              "uid": "35240-223fc079-2729-4445-855d-b7becf45b8f5"
                            }
                          ],
                          "createdAt": "2026-06-05T15:18:36.000Z",
                          "updatedAt": "2026-06-05T15:18:36.000Z",
                          "uid": "35240-6a4a5a2b-69c8-48a2-bacb-81e679456bb1"
                        }
                      ],
                      "id": "f2689d16-37c1-4efd-bacd-9d680a43455f",
                      "createdAt": "2026-06-05T15:18:36.000Z",
                      "updatedAt": "2026-06-05T15:18:36.000Z",
                      "uid": "35240-f2689d16-37c1-4efd-bacd-9d680a43455f"
                    }
                  ],
                  "id": "0483f3bc-9349-4332-b3ea-72405b9763bc",
                  "createdAt": "2026-06-05T15:18:36.000Z",
                  "updatedAt": "2026-06-05T15:18:36.000Z",
                  "uid": "35240-0483f3bc-9349-4332-b3ea-72405b9763bc"
                }
              ],
              "id": "1adece23-1ca0-4054-a80a-2833f79b9f11",
              "createdAt": "2026-06-05T15:18:36.000Z",
              "updatedAt": "2026-06-05T15:18:36.000Z",
              "uid": "35240-1adece23-1ca0-4054-a80a-2833f79b9f11"
            },
            {
              "name": "resourceGroups",
              "item": [
                {
                  "name": "{resourceGroupName}",
                  "item": [
                    {
                      "name": "providers",
                      "item": [
                        {
                          "name": "microsoft.insights",
                          "item": [
                            {
                              "name": "guestDiagnosticSettingsAssociations",
                              "item": [
                                {
                                  "name": "Microsoft Azure Get Subscriptions Subscriptionid Resourcegroups Resourcegroupname Providers Microsoft Insights Guestdiagnosticsettingsassociations",
                                  "id": "bfec5b8e-e17a-44c0-b578-dd32873c2fec",
                                  "protocolProfileBehavior": {
                                    "disableBodyPruning": true
                                  },
                                  "request": {
                                    "method": "GET",
                                    "header": [
                                      {
                                        "key": "Accept",
                                        "value": "application/json"
                                      }
                                    ],
                                    "url": {
                                      "raw": "{{baseUrl}}/subscriptions/:subscriptionId/resourceGroups/:resourceGroupName/providers/microsoft.insights/guestDiagnosticSettingsAssociations",
                                      "host": [
                                        "{{baseUrl}}"
                                      ],
                                      "path": [
                                        "subscriptions",
                                        ":subscriptionId",
                                        "resourceGroups",
                                        ":resourceGroupName",
                                        "providers",
                                        "microsoft.insights",
                                        "guestDiagnosticSettingsAssociations"
                                      ],
                                      "variable": [
                                        {
                                          "id": "95bf6be5-4fa4-49ee-845f-15ab0c0293eb",
                                          "key": "subscriptionId"
                                        },
                                        {
                                          "id": "b6021d44-b822-4cac-bf60-c03a3477a1af",
                                          "key": "resourceGroupName"
                                        }
                                      ]
                                    },
                                    "description": "Get a list of all guest diagnostic settings association in a resource group."
                                  },
                                  "response": [
                                    {
                                      "id": "287ae826-3580-4388-8149-5755aaaa68e8",
                                      "name": "The request succeeded.",
                                      "originalRequest": {
                                        "method": "GET",
                                        "header": [
                                          {
                                            "key": "Accept",
                                            "value": "application/json"
                                          },
                                          {
                                            "description": "Added as a part of security scheme: oauth2",
                                            "key": "Authorization",
                                            "value": "<token>"
                                          }
                                        ],
                                        "url": {
                                          "raw": "{{baseUrl}}/subscriptions/:subscriptionId/resourceGroups/:resourceGroupName/providers/microsoft.insights/guestDiagnosticSettingsAssociations",
                                          "host": [
                                            "{{baseUrl}}"
                                          ],
                                          "path": [
                                            "subscriptions",
                                            ":subscriptionId",
                                            "resourceGroups",
                                            ":resourceGroupName",
                                            "providers",
                                            "microsoft.insights",
                                            "guestDiagnosticSettingsAssociations"
                                          ],
                                          "variable": [
                                            {
                                              "key": "subscriptionId"
                                            },
                                            {
                                              "key": "resourceGroupName"
                                            }
                                          ]
                                        }
                                      },
                                      "status": "OK",
                                      "code": 200,
                                      "_postman_previewlanguage": "json",
                                      "header": [
                                        {
                                          "key": "Content-Type",
                                          "value": "application/json"
                                        }
                                      ],
                                      "cookie": [],
                                      "responseTime": null,
                                      "body": "{\n  \"value\": [\n    {\n      \"location\": \"<string>\",\n      \"properties\": {},\n      \"id\": \"<string>\",\n      \"name\": \"<string>\",\n      \"type\": \"<string>\",\n      \"tags\": {\n        \"Duis_4ce\": \"<string>\",\n        \"eaa2\": \"<string>\"\n      }\n    },\n    {\n      \"location\": \"<string>\",\n      \"properties\": {},\n      \"id\": \"<string>\",\n      \"name\": \"<string>\",\n      \"type\": \"<string>\",\n      \"tags\": {\n        \"ametb\": \"<string>\",\n        \"consequat_8\": \"<string>\",\n        \"Excepteur_de\": \"<string>\"\n      }\n    }\n  ],\n  \"nextLink\": \"<string>\"\n}",
                                      "createdAt": "2026-06-05T15:18:36.000Z",
                                      "updatedAt": "2026-06-05T15:18:36.000Z",
                                      "uid": "35240-287ae826-3580-4388-8149-5755aaaa68e8"
                                    },
                                    {
                                      "id": "14b681c5-7b10-48c2-96f9-773af827939c",
                                      "name": "An error occurred and the list of guest diagnostic settings association could not be retrieved.",
                                      "originalRequest": {
                                        "method": "GET",
                                        "header": [
                                          {
                                            "key": "Accept",
                                            "value": "application/json"
                                          },
                                          {
                                            "description": "Added as a part of security scheme: oauth2",
                                            "key": "Authorization",
                                            "value": "<token>"
                                          }
                                        ],
                                        "url": {
                                          "raw": "{{baseUrl}}/subscriptions/:subscriptionId/resourceGroups/:resourceGroupName/providers/microsoft.insights/guestDiagnosticSettingsAssociations",
                                          "host": [
                                            "{{baseUrl}}"
                                          ],
                                          "path": [
                                            "subscriptions",
                                            ":subscriptionId",
                                            "resourceGroups",
                                            ":resourceGroupName",
                                            "providers",
                                            "microsoft.insights",
                                            "guestDiagnosticSettingsAssociations"
                                          ],
                                          "variable": [
                                            {
                                              "key": "subscriptionId"
                                            },
                                            {
                                              "key": "resourceGroupName"
                                            }
                                          ]
                                        }
                                      },
                                      "status": "Internal Server Error",
                                      "code": 500,
                                      "_postman_previewlanguage": "json",
                                      "header": [
                                        {
                                          "key": "Content-Type",
                                          "value": "application/json"
                                        }
                                      ],
                                      "cookie": [],
                                      "responseTime": null,
                                      "body": "{\n  \"code\": \"<string>\",\n  \"message\": \"<string>\"\n}",
                                      "createdAt": "2026-06-05T15:18:36.000Z",
                                      "updatedAt": "2026-06-05T15:18:36.000Z",
                                      "uid": "35240-14b681c5-7b10-48c2-96f9-773af827939c"
                                    }
                                  ],
                                  "createdAt": "2026-06-05T15:18:36.000Z",
                                  "updatedAt": "2026-06-05T15:18:36.000Z",
                                  "uid": "35240-bfec5b8e-e17a-44c0-b578-dd32873c2fec"
                                }
                              ],
                              "id": "e6584e94-3f09-4d54-b529-50abc36e2a99",
                              "createdAt": "2026-06-05T15:18:36.000Z",
                              "updatedAt": "2026-06-05T15:18:36.000Z",
                              "uid": "35240-e6584e94-3f09-4d54-b529-50abc36e2a99"
                            }
                          ],
                          "id": "8b66d3cb-583f-49f3-bbf6-baa08c7ae9a2",
                          "createdAt": "2026-06-05T15:18:36.000Z",
                          "updatedAt": "2026-06-05T15:18:36.000Z",
                          "uid": "35240-8b66d3cb-583f-49f3-bbf6-baa08c7ae9a2"
                        }
                      ],
                      "id": "c36e77aa-c471-48c1-96d7-2b1a885f3ba5",
                      "createdAt": "2026-06-05T15:18:36.000Z",
                      "updatedAt": "2026-06-05T15:18:36.000Z",
                      "uid": "35240-c36e77aa-c471-48c1-96d7-2b1a885f3ba5"
                    }
                  ],
                  "id": "ecaab014-e4f3-4f46-8023-4e4f57ca6019",
                  "createdAt": "2026-06-05T15:18:36.000Z",
                  "updatedAt": "2026-06-05T15:18:36.000Z",
                  "uid": "35240-ecaab014-e4f3-4f46-8023-4e4f57ca6019"
                }
              ],
              "id": "1bab15bc-3366-42fa-8ea2-ff41636186b5",
              "createdAt": "2026-06-05T15:18:36.000Z",
              "updatedAt": "2026-06-05T15:18:36.000Z",
              "uid": "35240-1bab15bc-3366-42fa-8ea2-ff41636186b5"
            }
          ],
          "id": "2c0fa563-5216-496d-af07-af035f352e3e",
          "createdAt": "2026-06-05T15:18:36.000Z",
          "updatedAt": "2026-06-05T15:18:36.000Z",
          "uid": "35240-2c0fa563-5216-496d-af07-af035f352e3e"
        }
      ],
      "id": "3899ee2f-96c0-4bc4-ba28-de73b9f4f9d4",
      "createdAt": "2026-06-05T15:18:36.000Z",
      "updatedAt": "2026-06-05T15:18:36.000Z",
      "uid": "35240-3899ee2f-96c0-4bc4-ba28-de73b9f4f9d4"
    }
  ],
  "auth": {
    "type": "oauth2",
    "oauth2": [
      {
        "key": "scope",
        "value": "user_impersonation",
        "type": "string"
      },
      {
        "key": "authUrl",
        "value": "https://login.microsoftonline.com/common/oauth2/authorize",
        "type": "string"
      },
      {
        "key": "grant_type",
        "value": "implicit",
        "type": "string"
      }
    ]
  },
  "variable": [
    {
      "key": "baseUrl",
      "value": "https://management.azure.com"
    }
  ]
}