{
  "$schema": "https://json-schema.org/draft/2020-12/schema",
  "title": "SecretAttributes",
  "type": "object",
  "description": "The secret management attributes.",
  "properties": {
    "enabled": {
      "type": "boolean",
      "description": "Whether the secret is enabled."
    },
    "nbf": {
      "type": "integer",
      "description": "Not before date in UTC (Unix time)."
    },
    "exp": {
      "type": "integer",
      "description": "Expiry date in UTC (Unix time)."
    },
    "created": {
      "type": "integer",
      "description": "Creation time in UTC (Unix time)."
    },
    "updated": {
      "type": "integer",
      "description": "Last updated time in UTC (Unix time)."
    },
    "recoveryLevel": {
      "type": "string",
      "description": "The recovery level currently in effect."
    },
    "recoverableDays": {
      "type": "integer",
      "description": "The soft-delete data retention days."
    }
  }
}